{
  "id": "psychology.biological-psychology.chapter-10.topic-03",
  "name": "Heritability",
  "subject": "psychology",
  "definition": "Heritability is a fundamental concept in psychology.",
  "explanation": "Learn about Heritability and its applications.",
  "prerequisites": [],
  "relatedConcepts": [],
  "visualizationIds": [],
  "quizIds": [],
  "flashcardIds": [],
  "exampleIds": [],
  "exerciseIds": [],
  "difficulty": "beginner",
  "estimatedMinutes": 10,
  "tags": [
    "psychology",
    "heritability"
  ]
}