{
  "id": "computer-science.programming-fundamentals.chapter-13.topic-10",
  "name": "Constructors",
  "subject": "computer-science",
  "definition": "Constructors is a fundamental concept in computer-science.",
  "explanation": "Learn about Constructors and its applications.",
  "prerequisites": [],
  "relatedConcepts": [],
  "visualizationIds": [],
  "quizIds": [],
  "flashcardIds": [],
  "exampleIds": [],
  "exerciseIds": [],
  "difficulty": "beginner",
  "estimatedMinutes": 10,
  "tags": [
    "computer-science",
    "constructors"
  ]
}