{
  "id": "mathematics.pre-algebra.chapter-08.topic-04",
  "name": "Checking Solutions",
  "subject": "mathematics",
  "definition": "Checking Solutions is a fundamental concept in mathematics.",
  "explanation": "Learn about Checking Solutions and its applications.",
  "prerequisites": [],
  "relatedConcepts": [],
  "visualizationIds": [],
  "quizIds": [],
  "flashcardIds": [],
  "exampleIds": [],
  "exerciseIds": [],
  "difficulty": "beginner",
  "estimatedMinutes": 10,
  "tags": [
    "mathematics",
    "checking-solutions"
  ]
}