{
  "id": "physics.electricity-electrostatics.chapter-01.topic-02",
  "name": "Types of Charge",
  "subject": "physics",
  "definition": "Types of Charge is a fundamental concept in physics.",
  "explanation": "Learn about Types of Charge and its applications.",
  "prerequisites": [],
  "relatedConcepts": [],
  "visualizationIds": [],
  "quizIds": [],
  "flashcardIds": [],
  "exampleIds": [],
  "exerciseIds": [],
  "difficulty": "beginner",
  "estimatedMinutes": 10,
  "tags": [
    "physics",
    "types-of-charge"
  ]
}