{
  "id": "mathematics.discrete-mathematics.chapter-08.topic-04",
  "name": "Characteristic Equations",
  "subject": "mathematics",
  "definition": "Characteristic Equations is a fundamental concept in mathematics.",
  "explanation": "Learn about Characteristic Equations and its applications.",
  "prerequisites": [],
  "relatedConcepts": [],
  "visualizationIds": [],
  "quizIds": [],
  "flashcardIds": [],
  "exampleIds": [],
  "exerciseIds": [],
  "difficulty": "beginner",
  "estimatedMinutes": 10,
  "tags": [
    "mathematics",
    "characteristic-equations"
  ]
}