{
  "id": "physics.work-energy-power.chapter-06.topic-06",
  "name": "Power in Machines",
  "subject": "physics",
  "definition": "Power in Machines is a fundamental concept in physics.",
  "explanation": "Learn about Power in Machines and its applications.",
  "prerequisites": [],
  "relatedConcepts": [],
  "visualizationIds": [],
  "quizIds": [],
  "flashcardIds": [],
  "exampleIds": [],
  "exerciseIds": [],
  "difficulty": "beginner",
  "estimatedMinutes": 10,
  "tags": [
    "physics",
    "power-in-machines"
  ]
}