{
  "id": "psychology.industrial-organizational-psychology.chapter-09.topic-03",
  "name": "Occupational Stress",
  "subject": "psychology",
  "definition": "Occupational Stress is a fundamental concept in psychology.",
  "explanation": "Learn about Occupational Stress and its applications.",
  "prerequisites": [],
  "relatedConcepts": [],
  "visualizationIds": [],
  "quizIds": [],
  "flashcardIds": [],
  "exampleIds": [],
  "exerciseIds": [],
  "difficulty": "beginner",
  "estimatedMinutes": 10,
  "tags": [
    "psychology",
    "occupational-stress"
  ]
}