{
  "id": "physics.fluid-mechanics.chapter-08.topic-06",
  "name": "Capillary Rise",
  "subject": "physics",
  "definition": "Capillary Rise is a fundamental concept in physics.",
  "explanation": "Learn about Capillary Rise and its applications.",
  "prerequisites": [],
  "relatedConcepts": [],
  "visualizationIds": [],
  "quizIds": [],
  "flashcardIds": [],
  "exampleIds": [],
  "exerciseIds": [],
  "difficulty": "beginner",
  "estimatedMinutes": 10,
  "tags": [
    "physics",
    "capillary-rise"
  ]
}