{
  "id": "economics.monetary-economics.chapter-03.topic-07",
  "name": "Credit Creation",
  "subject": "economics",
  "definition": "Credit Creation is a fundamental concept in economics.",
  "explanation": "Learn about Credit Creation and its applications.",
  "prerequisites": [],
  "relatedConcepts": [],
  "visualizationIds": [],
  "quizIds": [],
  "flashcardIds": [],
  "exampleIds": [],
  "exerciseIds": [],
  "difficulty": "beginner",
  "estimatedMinutes": 10,
  "tags": [
    "economics",
    "credit-creation"
  ]
}