{
  "id": "economics.international-economics.chapter-03.topic-04",
  "name": "New Trade Theory",
  "subject": "economics",
  "definition": "New Trade Theory is a fundamental concept in economics.",
  "explanation": "Learn about New Trade Theory and its applications.",
  "prerequisites": [],
  "relatedConcepts": [],
  "visualizationIds": [],
  "quizIds": [],
  "flashcardIds": [],
  "exampleIds": [],
  "exerciseIds": [],
  "difficulty": "beginner",
  "estimatedMinutes": 10,
  "tags": [
    "economics",
    "new-trade-theory"
  ]
}