{
  "id": "economics.development-economics.chapter-08.topic-04",
  "name": "Nutrition",
  "subject": "economics",
  "definition": "Nutrition is a fundamental concept in economics.",
  "explanation": "Learn about Nutrition and its applications.",
  "prerequisites": [],
  "relatedConcepts": [],
  "visualizationIds": [],
  "quizIds": [],
  "flashcardIds": [],
  "exampleIds": [],
  "exerciseIds": [],
  "difficulty": "beginner",
  "estimatedMinutes": 10,
  "tags": [
    "economics",
    "nutrition"
  ]
}