{
  "id": "physics.gravitation.chapter-06.topic-05",
  "name": "Satellite Launch",
  "subject": "physics",
  "definition": "Satellite Launch is a fundamental concept in physics.",
  "explanation": "Learn about Satellite Launch and its applications.",
  "prerequisites": [],
  "relatedConcepts": [],
  "visualizationIds": [],
  "quizIds": [],
  "flashcardIds": [],
  "exampleIds": [],
  "exerciseIds": [],
  "difficulty": "beginner",
  "estimatedMinutes": 10,
  "tags": [
    "physics",
    "satellite-launch"
  ]
}