{
  "id": "physics.quantum-mechanics.chapter-03.topic-04",
  "name": "Stationary States",
  "subject": "physics",
  "definition": "Stationary States is a fundamental concept in physics.",
  "explanation": "Learn about Stationary States and its applications.",
  "prerequisites": [],
  "relatedConcepts": [],
  "visualizationIds": [],
  "quizIds": [],
  "flashcardIds": [],
  "exampleIds": [],
  "exerciseIds": [],
  "difficulty": "beginner",
  "estimatedMinutes": 10,
  "tags": [
    "physics",
    "stationary-states"
  ]
}