{
  "id": "biology.biotechnology.chapter-12.topic-02",
  "name": "Cancer Therapy",
  "subject": "biology",
  "definition": "Cancer Therapy is a fundamental concept in biology.",
  "explanation": "Learn about Cancer Therapy and its applications.",
  "prerequisites": [],
  "relatedConcepts": [],
  "visualizationIds": [],
  "quizIds": [],
  "flashcardIds": [],
  "exampleIds": [],
  "exerciseIds": [],
  "difficulty": "beginner",
  "estimatedMinutes": 10,
  "tags": [
    "biology",
    "cancer-therapy"
  ]
}