{
  "id": "computer-science.data-structures.chapter-05.topic-02",
  "name": "Queue Operations",
  "subject": "computer-science",
  "definition": "Queue Operations is a fundamental concept in computer-science.",
  "explanation": "Learn about Queue Operations and its applications.",
  "prerequisites": [],
  "relatedConcepts": [],
  "visualizationIds": [],
  "quizIds": [],
  "flashcardIds": [],
  "exampleIds": [],
  "exerciseIds": [],
  "difficulty": "beginner",
  "estimatedMinutes": 10,
  "tags": [
    "computer-science",
    "queue-operations"
  ]
}