{
  "id": "mathematics.geometry.chapter-02.topic-01",
  "name": "Types of Angles",
  "subject": "mathematics",
  "definition": "Types of Angles is a fundamental concept in mathematics.",
  "explanation": "Learn about Types of Angles and its applications.",
  "prerequisites": [],
  "relatedConcepts": [],
  "visualizationIds": [],
  "quizIds": [],
  "flashcardIds": [],
  "exampleIds": [],
  "exerciseIds": [],
  "difficulty": "beginner",
  "estimatedMinutes": 10,
  "tags": [
    "mathematics",
    "types-of-angles"
  ]
}