{
  "id": "mathematics.differential-equations.chapter-11.topic-03",
  "name": "Laplace Equation",
  "subject": "mathematics",
  "definition": "Laplace Equation is a fundamental concept in mathematics.",
  "explanation": "Learn about Laplace Equation and its applications.",
  "prerequisites": [],
  "relatedConcepts": [],
  "visualizationIds": [],
  "quizIds": [],
  "flashcardIds": [],
  "exampleIds": [],
  "exerciseIds": [],
  "difficulty": "beginner",
  "estimatedMinutes": 10,
  "tags": [
    "mathematics",
    "laplace-equation"
  ]
}