{
  "id": "philosophy.political-philosophy.chapter-03.topic-06",
  "name": "Human Dignity",
  "subject": "philosophy",
  "definition": "Human Dignity is a fundamental concept in philosophy.",
  "explanation": "Learn about Human Dignity and its applications.",
  "prerequisites": [],
  "relatedConcepts": [],
  "visualizationIds": [],
  "quizIds": [],
  "flashcardIds": [],
  "exampleIds": [],
  "exerciseIds": [],
  "difficulty": "beginner",
  "estimatedMinutes": 10,
  "tags": [
    "philosophy",
    "human-dignity"
  ]
}