{
  "id": "philosophy.metaphysics.chapter-03.topic-03",
  "name": "Absolute vs Relative Space",
  "subject": "philosophy",
  "definition": "Absolute vs Relative Space is a fundamental concept in philosophy.",
  "explanation": "Learn about Absolute vs Relative Space and its applications.",
  "prerequisites": [],
  "relatedConcepts": [],
  "visualizationIds": [],
  "quizIds": [],
  "flashcardIds": [],
  "exampleIds": [],
  "exerciseIds": [],
  "difficulty": "beginner",
  "estimatedMinutes": 10,
  "tags": [
    "philosophy",
    "absolute-vs-relative-space"
  ]
}