{
  "id": "computer-science.computer-graphics.chapter-07.topic-04",
  "name": "Specular Lighting",
  "subject": "computer-science",
  "definition": "Specular Lighting is a fundamental concept in computer-science.",
  "explanation": "Learn about Specular Lighting and its applications.",
  "prerequisites": [],
  "relatedConcepts": [],
  "visualizationIds": [],
  "quizIds": [],
  "flashcardIds": [],
  "exampleIds": [],
  "exerciseIds": [],
  "difficulty": "beginner",
  "estimatedMinutes": 10,
  "tags": [
    "computer-science",
    "specular-lighting"
  ]
}