{
  "id": "philosophy.logic.chapter-13.topic-01",
  "name": "Set Theory (Introduction)",
  "subject": "philosophy",
  "definition": "Set Theory (Introduction) is a fundamental concept in philosophy.",
  "explanation": "Learn about Set Theory (Introduction) and its applications.",
  "prerequisites": [],
  "relatedConcepts": [],
  "visualizationIds": [],
  "quizIds": [],
  "flashcardIds": [],
  "exampleIds": [],
  "exerciseIds": [],
  "difficulty": "beginner",
  "estimatedMinutes": 10,
  "tags": [
    "philosophy",
    "set-theory-introduction"
  ]
}